ee_jupyter/__init__.py
ee_jupyter/_modidx.py
ee_jupyter/colab.py
ee_jupyter/core.py
ee_jupyter/ipyleaflet.py
ee_jupyter/layout.py
ee_jupyter/rich_display.py
earthengine_jupyter-0.0.7.dist-info/LICENSE
earthengine_jupyter-0.0.7.dist-info/METADATA
earthengine_jupyter-0.0.7.dist-info/WHEEL
earthengine_jupyter-0.0.7.dist-info/entry_points.txt
earthengine_jupyter-0.0.7.dist-info/top_level.txt
earthengine_jupyter-0.0.7.dist-info/RECORD
