Metadata-Version: 2.1
Name: earthengine-jupyter
Version: 0.0.7
Summary: Tools for working with the Earth Engine from a Jupyter development environment
Home-page: https://github.com/google/earthengine-jupyter
Author: tylere
Author-email: tylere@google.com
License: Apache Software License 2.0
Keywords: nbdev jupyter notebook python
Classifier: Development Status :: 4 - Beta
Classifier: Intended Audience :: Developers
Classifier: Natural Language :: English
Classifier: Programming Language :: Python :: 3.7
Classifier: Programming Language :: Python :: 3.8
Classifier: Programming Language :: Python :: 3.9
Classifier: Programming Language :: Python :: 3.10
Classifier: License :: OSI Approved :: Apache Software License
Requires-Python: >=3.7
License-File: LICENSE
Requires-Dist: earthengine-api
Requires-Dist: jupyter
Requires-Dist: ipyleaflet
Requires-Dist: ipytree
Provides-Extra: dev
